<annotation>
	<folder>train</folder>
	<filename>38.jpg</filename>
	<path>D:\Internship\Happiness\train\38.jpg</path>
	<source>
		<database>Unknown</database>
	</source>
	<size>
		<width>604</width>
		<height>806</height>
		<depth>3</depth>
	</size>
	<segmented>0</segmented>
	<object>
		<name>Void</name>
		<pose>Unspecified</pose>
		<truncated>0</truncated>
		<difficult>0</difficult>
		<bndbox>
			<xmin>9</xmin>
			<ymin>16</ymin>
			<xmax>465</xmax>
			<ymax>451</ymax>
		</bndbox>
	</object>
	<object>
		<name>Label</name>
		<pose>Unspecified</pose>
		<truncated>0</truncated>
		<difficult>0</difficult>
		<bndbox>
			<xmin>71</xmin>
			<ymin>638</ymin>
			<xmax>261</xmax>
			<ymax>754</ymax>
		</bndbox>
	</object>
	<object>
		<name>Time</name>
		<pose>Unspecified</pose>
		<truncated>1</truncated>
		<difficult>0</difficult>
		<bndbox>
			<xmin>145</xmin>
			<ymin>1</ymin>
			<xmax>604</xmax>
			<ymax>58</ymax>
		</bndbox>
	</object>
	<object>
		<name>Location</name>
		<pose>Unspecified</pose>
		<truncated>1</truncated>
		<difficult>0</difficult>
		<bndbox>
			<xmin>350</xmin>
			<ymin>82</ymin>
			<xmax>604</xmax>
			<ymax>198</ymax>
		</bndbox>
	</object>
</annotation>
